econdata/BCRP.py
econdata/FRED.py
econdata/IMF.py
econdata/OECD.py
econdata/WB.py
econdata/YFinance.py
econdata/__init__.py
econdata-1.0.17.dist-info/LICENSE
econdata-1.0.17.dist-info/METADATA
econdata-1.0.17.dist-info/WHEEL
econdata-1.0.17.dist-info/top_level.txt
econdata-1.0.17.dist-info/RECORD
