Metadata-Version: 2.1
Name: econdata
Version: 1.0.17
Summary: Extracción de series de tiempo de las principales instituciones económicas para el Perú
Home-page: https://github.com/mauricioalvaradoo/econdata
Author: Mauricio Alvarado
Classifier: Programming Language :: Python :: 3
Classifier: License :: OSI Approved :: MIT License
Classifier: Operating System :: OS Independent
Requires-Python: >=3.6
License-File: LICENSE
Requires-Dist: pandas
Requires-Dist: numpy
Requires-Dist: yfinance
Requires-Dist: requests
Requires-Dist: warn
Requires-Dist: more-itertools
